Workbook

Sheet 01_Dashboard
A1: Scenario Selector | B1: Active Status Indicator | I1: =IF('02_Forecast_24M'!$C$40="PASS", "🟢 MODEL INTEGRITY: OK", "🔴 AUDIT FAILURE: RECONCILE ENGINE") -> 🟢 MODEL INTEGRITY: OK
A2: Base | B2: =IFS(A2="Base", "🔵 Management Plan", A2="Bull", "🟢 Growth Sprint", A2="Bear", "🔴 Stress test", TRUE, "-") -> 🔵 Management Plan
B4: CASH RUNWAY | D4: ZERO-CASH MONTH | F4: AVG MONTHLY BURN | H4: LTV : CAC RATIO
B5: =IF(COUNTIF('02_Forecast_24M'!D34:AA34, "=SOLVENT")=24, "24+ Months", COUNTIF('02_Forecast_24M'!D34:AA34, "SOLVENT") & " Months") -> 24+ Months | D5: =IF(COUNTIF('02_Forecast_24M'!D33:AA33, "<0")=0, "Fully Funded", "Month " & COUNTIF('02_Forecast_24M'!D33:AA33, ">=0")+1) -> Fully Funded | F5: =IF(COUNTIF('02_Forecast_24M'!D30:AA30, "<0")=0, "$0 (Profitable)", TEXT(AVERAGEIF('02_Forecast_24M'!D30:AA30, "<0"), "$#, ##0")) -> $0 (Profitable) | H5: =ROUND((('03_Assumptions'!F10*'02_Forecast_24M'!D20)/(1-'03_Assumptions'!F7))/(('03_Assumptions'!F22/'02_Forecast_24M'!D4)), 1) & "x" -> 47.4x
B6: Target Threshold : 18+ Months | D6: Point of External Capital Required | H6: Benchmark: > 3.0x is healthy
A29: SCENARIO COMPARISON MATRIX | B29: BEAR CASE | C29: BASE CASE | D29: BULL CASE | E29: STRATEGIC TAKEAWAY
A30: Cash Runaway (Months) | B30: 8 Months | C30: 24+ Months | D30: 24+ Months | E30: Bear requires early bridge round by M6; Base/Bull Self-fund indefinitely
A31: Operating Breakeven Month | B31: N/A (> 24M) | C31: Month 1 | D31: Month 1 | E31: Base/Bull generate immediate operational cash surplus; Bear operates at a persistent deficit
A32: Peak Cash Deficit / Min Cash | B32: -84669.373 | C32: 159665.62 | D32: 267957.88 | E32: Max downside capital risk capped at ~$84.7k under severe 92% Retention
A33: Month 24 Ending Cash Balance | B33: -84669.373 | C33: 2278028.8 | D33: 13908931 | E33: Bull scales treasury reserves above $13.9M; provides aggressive R&D capacity
A34: Cumulative 24M Net Revenue | B34: 755025.6 | C34: 3748550 | D34: 16716521 | E34: 22x times more revenue

Sheet 02_Forecast_24M
A1: Line Item ID | B1: Line Item Name | C1: Unit / Measurement | D1: Month 1 | E1: Month 2 | F1: Month 3 | G1: Month 4 | H1: Month 5 | I1: Month 6 | J1: Month 7 | K1: Month 8 | L1: Month 9 | M1: Month 10 | N1: Month 11 | O1: Month 12 | P1: Month 13 | Q1: Month 14 | R1: Month 15 | S1: Month 16 | T1: Month 17 | U1: Month 18 | V1: Month 19 | W1: Month 20 | X1: Month 21 | Y1: Month 22 | Z1: Month 23 | AA1: Month 24
A2: 1. CUSTOMER DYNAMICS
A3: CUST-01 | B3: Beginning Active Customers | C3: Users | D3: ='03_Assumptions'!F4 -> 1000 | E3: =D6 -> 1250 | F3: =E6 -> 1487 | G3: =F6 -> 1713 | H3: =G6 -> 1927 | I3: =H6 -> 2131 | J3: =I6 -> 2324 | K3: =J6 -> 2508 | L3: =K6 -> 2683 | ... AA3: =Z6 -> 4463
A4: CUST-02 | B4: New Customers Acquired | C4: Users | D4: ='03_Assumptions'!$F$5*'03_Assumptions'!$F$6 -> 300 | E4: ='03_Assumptions'!$F$5*'03_Assumptions'!$F$6 -> 300 | F4: ='03_Assumptions'!$F$5*'03_Assumptions'!$F$6 -> 300 | G4: ='03_Assumptions'!$F$5*'03_Assumptions'!$F$6 -> 300 | H4: ='03_Assumptions'!$F$5*'03_Assumptions'!$F$6 -> 300 | I4: ='03_Assumptions'!$F$5*'03_Assumptions'!$F$6 -> 300 | J4: ='03_Assumptions'!$F$5*'03_Assumptions'!$F$6 -> 300 | K4: ='03_Assumptions'!$F$5*'03_Assumptions'!$F$6 -> 300 | ... AA4: ='03_Assumptions'!$F$5*'03_Assumptions'!$F$6 -> 300
A5: CUST-03 | B5: Churned Customers | C5: Users | D5: =-ROUND(D3*(1-'03_Assumptions'!$F$7), 0) -> -50 | E5: =-ROUND(E3*(1-'03_Assumptions'!$F$7), 0) -> -63 | F5: =-ROUND(F3*(1-'03_Assumptions'!$F$7), 0) -> -74 | G5: =-ROUND(G3*(1-'03_Assumptions'!$F$7), 0) -> -86 | H5: =-ROUND(H3*(1-'03_Assumptions'!$F$7), 0) -> -96 | I5: =-ROUND(I3*(1-'03_Assumptions'!$F$7), 0) -> -107 | J5: =-ROUND(J3*(1-'03_Assumptions'!$F$7), 0) -> -116 | K5: =-ROUND(K3*(1-'03_Assumptions'!$F$7), 0) -> -125 | ... AA5: =-ROUND(AA3*(1-'03_Assumptions'!$F$7), 0) -> -223
A6: CUST-04 | B6: Ending Active Customers | C6: Users | D6: =SUM(D3:D5) -> 1250 | E6: =SUM(E3:E5) -> 1487 | F6: =SUM(F3:F5) -> 1713 | G6: =SUM(G3:G5) -> 1927 | H6: =SUM(H3:H5) -> 2131 | I6: =SUM(I3:I5) -> 2324 | J6: =SUM(J3:J5) -> 2508 | K6: =SUM(K3:K5) -> 2683 | ... AA6: =SUM(AA3:AA5) -> 4540
A8: 2. REVENUE BUILD
A9: REV-01 | B9: Gross Subscription Revenue | C9: $ | D9: =(D3+D6)/2*'03_Assumptions'!$F$10 -> 56250 | E9: =(E3+E6)/2*'03_Assumptions'!$F$10 -> 68425 | F9: =(F3+F6)/2*'03_Assumptions'!$F$10 -> 80000 | G9: =(G3+G6)/2*'03_Assumptions'!$F$10 -> 91000 | H9: =(H3+H6)/2*'03_Assumptions'!$F$10 -> 101450 | I9: =(I3+I6)/2*'03_Assumptions'!$F$10 -> 111375 | J9: =(J3+J6)/2*'03_Assumptions'!$F$10 -> 120800 | K9: =(K3+K6)/2*'03_Assumptions'!$F$10 -> 129775 | ... AA9: =(AA3+AA6)/2*'03_Assumptions'!$F$10 -> 225075
A10: REV-02 | B10: Expansion Revenue | C10: $ | D10: =D9*'03_Assumptions'!$F$11 -> 2812.5 | E10: =E9*'03_Assumptions'!$F$11 -> 3421.25 | F10: =F9*'03_Assumptions'!$F$11 -> 4000 | G10: =G9*'03_Assumptions'!$F$11 -> 4550 | H10: =H9*'03_Assumptions'!$F$11 -> 5072.5 | I10: =I9*'03_Assumptions'!$F$11 -> 5568.75 | J10: =J9*'03_Assumptions'!$F$11 -> 6040 | K10: =K9*'03_Assumptions'!$F$11 -> 6488.75 | ... AA10: =AA9*'03_Assumptions'!$F$11 -> 11253.75
A11: REV-03 | B11: Discounts & Promotions | C11: $ | D11: =-D9*'03_Assumptions'!$F$12 -> -2812.5 | E11: =-E9*'03_Assumptions'!$F$12 -> -3421.25 | F11: =-F9*'03_Assumptions'!$F$12 -> -4000 | G11: =-G9*'03_Assumptions'!$F$12 -> -4550 | H11: =-H9*'03_Assumptions'!$F$12 -> -5072.5 | I11: =-I9*'03_Assumptions'!$F$12 -> -5568.75 | J11: =-J9*'03_Assumptions'!$F$12 -> -6040 | K11: =-K9*'03_Assumptions'!$F$12 -> -6488.75 | ... AA11: =-AA9*'03_Assumptions'!$F$12 -> -11253.75
A12: REV-04 | B12: Net Revenue | C12: $ | D12: =SUM(D9:D11) -> 56250 | E12: =SUM(E9:E11) -> 68425 | F12: =SUM(F9:F11) -> 80000 | G12: =SUM(G9:G11) -> 91000 | H12: =SUM(H9:H11) -> 101450 | I12: =SUM(I9:I11) -> 111375 | J12: =SUM(J9:J11) -> 120800 | K12: =SUM(K9:K11) -> 129775 | ... AA12: =SUM(AA9:AA11) -> 225075
A14: 3. COST OF GOODS SOLD (COGS)
A15: COGS-01 | B15: Payment Processing Fees | C15: $ | D15: =D12*'03_Assumptions'!$F$15 -> 1659.375 | E15: =E12*'03_Assumptions'!$F$15 -> 2018.5375 | F15: =F12*'03_Assumptions'!$F$15 -> 2360 | G15: =G12*'03_Assumptions'!$F$15 -> 2684.5 | H15: =H12*'03_Assumptions'!$F$15 -> 2992.775 | I15: =I12*'03_Assumptions'!$F$15 -> 3285.5625 | J15: =J12*'03_Assumptions'!$F$15 -> 3563.6 | K15: =K12*'03_Assumptions'!$F$15 -> 3828.3625 | ... AA15: =AA12*'03_Assumptions'!$F$15 -> 6639.7125
A16: COGS-02 | B16: Cloud Hosting & Infrastructure | C16: $ | D16: =((D3+D6)/2)*'03_Assumptions'!$F$17 -> 3375 | E16: =((E3+E6)/2)*'03_Assumptions'!$F$17 -> 4105.5 | F16: =((F3+F6)/2)*'03_Assumptions'!$F$17 -> 4800 | G16: =((G3+G6)/2)*'03_Assumptions'!$F$17 -> 5460 | H16: =((H3+H6)/2)*'03_Assumptions'!$F$17 -> 6087 | I16: =((I3+I6)/2)*'03_Assumptions'!$F$17 -> 6682.5 | J16: =((J3+J6)/2)*'03_Assumptions'!$F$17 -> 7248 | K16: =((K3+K6)/2)*'03_Assumptions'!$F$17 -> 7786.5 | ... AA16: =((AA3+AA6)/2)*'03_Assumptions'!$F$17 -> 13504.5
A17: COGS-03 | B17: Customer Support Costs | C17: $ | D17: =(D6+D3)/2*'03_Assumptions'!$F$16 -> 6750 | E17: =(E6+E3)/2*'03_Assumptions'!$F$16 -> 8211 | F17: =(F6+F3)/2*'03_Assumptions'!$F$16 -> 9600 | G17: =(G6+G3)/2*'03_Assumptions'!$F$16 -> 10920 | H17: =(H6+H3)/2*'03_Assumptions'!$F$16 -> 12174 | I17: =(I6+I3)/2*'03_Assumptions'!$F$16 -> 13365 | J17: =(J6+J3)/2*'03_Assumptions'!$F$16 -> 14496 | K17: =(K6+K3)/2*'03_Assumptions'!$F$16 -> 15573 | ... AA17: =(AA6+AA3)/2*'03_Assumptions'!$F$16 -> 27009
A18: COGS-04 | B18: Total COGS | C18: $ | D18: =SUM(D15:D17) -> 11784.375 | E18: =SUM(E15:E17) -> 14335.038 | F18: =SUM(F15:F17) -> 16760 | G18: =SUM(G15:G17) -> 19064.5 | H18: =SUM(H15:H17) -> 21253.775 | I18: =SUM(I15:I17) -> 23333.062 | J18: =SUM(J15:J17) -> 25307.6 | K18: =SUM(K15:K17) -> 27187.862 | ... AA18: =SUM(AA15:AA17) -> 47153.213
A19: COGS-05 | B19: Gross Profit | C19: $ | D19: =D12-D18 -> 44465.625 | E19: =E12-E18 -> 54089.963 | F19: =F12-F18 -> 63240 | G19: =G12-G18 -> 71935.5 | H19: =H12-H18 -> 80196.225 | I19: =I12-I18 -> 88041.938 | J19: =J12-J18 -> 95492.4 | K19: =K12-K18 -> 102587.14 | ... AA19: =AA12-AA18 -> 177921.79
A20: COGS-06 | B20: Gross Margin | C20: % | D20: =D19/D12 -> 0.7905 | E20: =E19/E12 -> 0.7905 | F20: =F19/F12 -> 0.7905 | G20: =G19/G12 -> 0.7905 | H20: =H19/H12 -> 0.7905 | I20: =I19/I12 -> 0.7905 | J20: =J19/J12 -> 0.7905 | K20: =K19/K12 -> 0.7905 | ... AA20: =AA19/AA12 -> 0.7905
A22: 4. OPERATING EXPENSES (OPEX)
A23: OPEX-01 | B23: Core Team Payroll | C23: $ | D23: ='03_Assumptions'!$F$21 -> 25000 | E23: ='03_Assumptions'!$F$21 -> 25000 | F23: ='03_Assumptions'!$F$21 -> 25000 | G23: ='03_Assumptions'!$F$21 -> 25000 | H23: ='03_Assumptions'!$F$21 -> 25000 | I23: ='03_Assumptions'!$F$21 -> 25000 | J23: ='03_Assumptions'!$F$21 -> 25000 | K23: ='03_Assumptions'!$F$21 -> 25000 | ... AA23: ='03_Assumptions'!$F$21 -> 25000
A24: OPEX-02 | B24: Paid Marketing Spend | C24: $ | D24: ='03_Assumptions'!$F$22 -> 5000 | E24: ='03_Assumptions'!$F$22 -> 5000 | F24: ='03_Assumptions'!$F$22 -> 5000 | G24: ='03_Assumptions'!$F$22 -> 5000 | H24: ='03_Assumptions'!$F$22 -> 5000 | I24: ='03_Assumptions'!$F$22 -> 5000 | J24: ='03_Assumptions'!$F$22 -> 5000 | K24: ='03_Assumptions'!$F$22 -> 5000 | ... AA24: ='03_Assumptions'!$F$22 -> 5000
A25: OPEX-03 | B25: Software Subscriptions & Tools | C25: $ | D25: ='03_Assumptions'!$F$23 -> 1800 | E25: ='03_Assumptions'!$F$23 -> 1800 | F25: ='03_Assumptions'!$F$23 -> 1800 | G25: ='03_Assumptions'!$F$23 -> 1800 | H25: ='03_Assumptions'!$F$23 -> 1800 | I25: ='03_Assumptions'!$F$23 -> 1800 | J25: ='03_Assumptions'!$F$23 -> 1800 | K25: ='03_Assumptions'!$F$23 -> 1800 | ... AA25: ='03_Assumptions'!$F$23 -> 1800
A26: OPEX-04 | B26: General Admin, Legal & Rent | C26: $ | D26: ='03_Assumptions'!$F$24 -> 3000 | E26: ='03_Assumptions'!$F$24 -> 3000 | F26: ='03_Assumptions'!$F$24 -> 3000 | G26: ='03_Assumptions'!$F$24 -> 3000 | H26: ='03_Assumptions'!$F$24 -> 3000 | I26: ='03_Assumptions'!$F$24 -> 3000 | J26: ='03_Assumptions'!$F$24 -> 3000 | K26: ='03_Assumptions'!$F$24 -> 3000 | ... AA26: ='03_Assumptions'!$F$24 -> 3000
A27: OPEX-05 | B27: Total OPEX | C27: $ | D27: =SUM(D23:D26) -> 34800 | E27: =SUM(E23:E26) -> 34800 | F27: =SUM(F23:F26) -> 34800 | G27: =SUM(G23:G26) -> 34800 | H27: =SUM(H23:H26) -> 34800 | I27: =SUM(I23:I26) -> 34800 | J27: =SUM(J23:J26) -> 34800 | K27: =SUM(K23:K26) -> 34800 | ... AA27: =SUM(AA23:AA26) -> 34800
A29: 5. CASH FLOW & RUNAWAY
A30: CASH-01 | B30: Operating Cash Flow (Net Monthly Burn) | C30: $ | D30: =D19-D27 -> 9665.625 | E30: =E19-E27 -> 19289.963 | F30: =F19-F27 -> 28440 | G30: =G19-G27 -> 37135.5 | H30: =H19-H27 -> 45396.225 | I30: =I19-I27 -> 53241.938 | J30: =J19-J27 -> 60692.4 | K30: =K19-K27 -> 67787.137 | ... AA30: =AA19-AA27 -> 143121.79
A31: CASH-02 | B31: Beginning Cash Balance | C31: $ | D31: ='03_Assumptions'!$F$20 -> 150000 | E31: =D33 -> 159665.62 | F31: =E33 -> 178955.59 | G31: =F33 -> 207395.59 | H31: =G33 -> 244531.09 | I31: =H33 -> 289927.31 | J31: =I33 -> 343169.25 | K31: =J33 -> 403861.65 | L31: =K33 -> 471648.79 | ... AA31: =Z33 -> 2134907
A32: CASH-03 | B32: Net Cash Flow for Month | C32: $ | D32: =D30 -> 9665.625 | E32: =E30 -> 19289.963 | F32: =F30 -> 28440 | G32: =G30 -> 37135.5 | H32: =H30 -> 45396.225 | I32: =I30 -> 53241.938 | J32: =J30 -> 60692.4 | K32: =K30 -> 67787.137 | ... AA32: =AA30 -> 143121.79
A33: CASH-04 | B33: Ending Cash Balance | C33: $ | D33: =D31+D32 -> 159665.62 | E33: =E31+E32 -> 178955.59 | F33: =F31+F32 -> 207395.59 | G33: =G31+G32 -> 244531.09 | H33: =H31+H32 -> 289927.31 | I33: =I31+I32 -> 343169.25 | J33: =J31+J32 -> 403861.65 | K33: =K31+K32 -> 471648.79 | ... AA33: =AA31+AA32 -> 2278028.8
A34: CASH-05 | B34: Solvency Status Flag | C34: Status | D34: =IF(D33>0, "SOLVENT", "CASH DEFICIT") -> SOLVENT | E34: =IF(E33>0, "SOLVENT", "CASH DEFICIT") -> SOLVENT | F34: =IF(F33>0, "SOLVENT", "CASH DEFICIT") -> SOLVENT | G34: =IF(G33>0, "SOLVENT", "CASH DEFICIT") -> SOLVENT | H34: =IF(H33>0, "SOLVENT", "CASH DEFICIT") -> SOLVENT | I34: =IF(I33>0, "SOLVENT", "CASH DEFICIT") -> SOLVENT | J34: =IF(J33>0, "SOLVENT", "CASH DEFICIT") -> SOLVENT | K34: =IF(K33>0, "SOLVENT", "CASH DEFICIT") -> SOLVENT | ... AA34: =IF(AA33>0, "SOLVENT", "CASH DEFICIT") -> SOLVENT
A35: CASH-06 | B35: Total Cash Outflows | C35: $ | D35: =D27+D18 -> 46584.375 | E35: =E27+E18 -> 49135.037 | F35: =F27+F18 -> 51560 | G35: =G27+G18 -> 53864.5 | H35: =H27+H18 -> 56053.775 | I35: =I27+I18 -> 58133.062 | J35: =J27+J18 -> 60107.6 | K35: =K27+K18 -> 61987.863 | ... AA35: =AA27+AA18 -> 81953.212
A37: 6. MODEL INTEGRITY & AUDIT CHECKS
A38: CHECK-01 | B38: Cash Rollover Integrity | C38: Check | D38: 0 | E38: =E31-D33 -> 0 | F38: =F31-E33 -> 0 | G38: =G31-F33 -> 0 | H38: =H31-G33 -> 0 | I38: =I31-H33 -> 0 | J38: =J31-I33 -> 0 | K38: =K31-J33 -> 0 | L38: =L31-K33 -> 0 | ... AA38: =AA31-Z33 -> 0
A39: CHECK-02 | B39: Customer Conversion Check | C39: Check | D39: =D3+D4+D5-D6 -> 0 | E39: =E3+E4+E5-E6 -> 0 | F39: =F3+F4+F5-F6 -> 0 | G39: =G3+G4+G5-G6 -> 0 | H39: =H3+H4+H5-H6 -> 0 | I39: =I3+I4+I5-I6 -> 0 | J39: =J3+J4+J5-J6 -> 0 | K39: =K3+K4+K5-K6 -> 0 | ... AA39: =AA3+AA4+AA5-AA6 -> 0
C40: =IF(AND(SUM(D38:AA38)=0, SUM(D39:AA39)=0), "PASS", "FAIL") -> PASS

Sheet 03_Assumptions
A1: Line Item | B1: Unit | C1: Bear Case | D1: Base Case | E1: Bull Case | F1: Active Model Input
A3: 1. CUSTOMER & VOLUME DRIVERS
A4: Starting user count | B4: Users | C4: 500 | D4: 1000 | E4: 1500 | F4: =IFS('01_Dashboard'!$A$2="Base", D4, '01_Dashboard'!$A$2="Bull", E4, '01_Dashboard'!$A$2="Bear", C4, TRUE, "-") -> 1000
A5: Monthly new visitor volume | B5: Visitors | C5: 6000 | D5: 12000 | E5: 25000 | F5: =IFS('01_Dashboard'!$A$2="Base", D5, '01_Dashboard'!$A$2="Bull", E5, '01_Dashboard'!$A$2="Bear", C5, TRUE, "-") -> 12000
A6: Lead-to-customer conversion rate | B6: % | C6: 0.015 | D6: 0.025 | E6: 0.04 | F6: =IFS('01_Dashboard'!$A$2="Base", D6, '01_Dashboard'!$A$2="Bull", E6, '01_Dashboard'!$A$2="Bear", C6, TRUE, "-") -> 0.025
A7: Monthly retention rates | B7: % | C7: 0.92 | D7: 0.95 | E7: 0.97 | F7: =IFS('01_Dashboard'!$A$2="Base", D7, '01_Dashboard'!$A$2="Bull", E7, '01_Dashboard'!$A$2="Bear", C7, TRUE, "-") -> 0.95
A9: 2. MONETIZATION & PRICING
A10: Average order value (AOV) | B10: $ / user | C10: 40 | D10: 50 | E10: 60 | F10: =IFS('01_Dashboard'!$A$2="Base", D10, '01_Dashboard'!$A$2="Bull", E10, '01_Dashboard'!$A$2="Bear", C10, TRUE, "-") -> 50
A11: Expansion rates | B11: % of MRR | C11: 0.02 | D11: 0.05 | E11: 0.1 | F11: =IFS('01_Dashboard'!$A$2="Base", D11, '01_Dashboard'!$A$2="Bull", E11, '01_Dashboard'!$A$2="Bear", C11, TRUE, "-") -> 0.05
A12: Expected discount rates | B12: % of Gross | C12: 0.1 | D12: 0.05 | E12: 0.02 | F12: =IFS('01_Dashboard'!$A$2="Base", D12, '01_Dashboard'!$A$2="Bull", E12, '01_Dashboard'!$A$2="Bear", C12, TRUE, "-") -> 0.05
A14: 3. DIRECT / VARIABLE COSTS
A15: Payment processor cut | B15: % of Revenue | C15: 0.038 | D15: 0.0295 | E15: 0.022 | F15: =IFS('01_Dashboard'!$A$2="Base", D15, '01_Dashboard'!$A$2="Bull", E15, '01_Dashboard'!$A$2="Bear", C15, TRUE, "-") -> 0.0295
A16: Customer Support cost per active user | B16: $ / user | C16: 8 | D16: 6 | E16: 4 | F16: =IFS('01_Dashboard'!$A$2="Base", D16, '01_Dashboard'!$A$2="Bull", E16, '01_Dashboard'!$A$2="Bear", C16, TRUE, "-") -> 6
A17: Cloud hosting cost per user | B17: $ / user | C17: 4 | D17: 3 | E17: 2 | F17: =IFS('01_Dashboard'!$A$2="Base", D17, '01_Dashboard'!$A$2="Bull", E17, '01_Dashboard'!$A$2="Bear", C17, TRUE, "-") -> 3
A19: 4. FIXED OPERATING EXPENSES & CAPITAL
A20: Starting Bank Balance | B20: $ | C20: 100000 | D20: 150000 | E20: 200000 | F20: =IFS('01_Dashboard'!$A$2="Base", D20, '01_Dashboard'!$A$2="Bull", E20, '01_Dashboard'!$A$2="Bear", C20, TRUE, "-") -> 150000
A21: Core Team Payroll (Monthly) | B21: $ / month | C21: 20000 | D21: 25000 | E21: 30000 | F21: =IFS('01_Dashboard'!$A$2="Base", D21, '01_Dashboard'!$A$2="Bull", E21, '01_Dashboard'!$A$2="Bear", C21, TRUE, "-") -> 25000
A22: Paid Marketing budget (Monthly) | B22: $ / month | C22: 3200 | D22: 5000 | E22: 10000 | F22: =IFS('01_Dashboard'!$A$2="Base", D22, '01_Dashboard'!$A$2="Bull", E22, '01_Dashboard'!$A$2="Bear", C22, TRUE, "-") -> 5000
A23: Software Subscriptions & Tools | B23: $ / month | C23: 1500 | D23: 1800 | E23: 2000 | F23: =IFS('01_Dashboard'!$A$2="Base", D23, '01_Dashboard'!$A$2="Bull", E23, '01_Dashboard'!$A$2="Bear", C23, TRUE, "-") -> 1800
A24: General Admin, Legal & Rent | B24: $ / month | C24: 3000 | D24: 3000 | E24: 3500 | F24: =IFS('01_Dashboard'!$A$2="Base", D24, '01_Dashboard'!$A$2="Bull", E24, '01_Dashboard'!$A$2="Bear", C24, TRUE, "-") -> 3000
